{
  "title": "International Workshop on Spoken Dialogue Systems Technology - ACL Anthology",
  "text": "International Workshop on Spoken Dialogue Systems Technology - ACL Anthology\nACL Anthology\nNews\n(current)\nFAQ\n(current)\nCorrections\n(current)\nSubmissions\n(current)\nGithub\nInternational Workshop on Spoken Dialogue Systems Technology (IWSDS)\nAcronym:\nIWSDS\nVenue ID:\niwsds\n2025\nProceedings of the 15th International Workshop on Spoken Dialogue Systems Technology\n38 papers\nACL materials are Copyright © 1963–2026 ACL; other materials are copyrighted by their respective copyright holders. Materials prior to 2016 here are licensed under the\nCreative Commons Attribution-NonCommercial-ShareAlike 3.0 International License\n. Permission is granted to make copies for the purposes of teaching and research. Materials published in or after 2016 are licensed on a\nCreative Commons Attribution 4.0 International License\n.\nThe ACL Anthology is managed and built by the\nACL Anthology team\nof volunteers.\nSite last built on 07 January 2026 at 14:08 UTC with\ncommit efd9fde\n.",
  "links": {
    "ACL Anthology": "https://aclanthology.org/",
    "News(current)": "/posts/",
    "FAQ(current)": "/faq/",
    "Corrections(current)": "/info/corrections/",
    "Submissions(current)": "/info/contrib/",
    "Github": "https://github.com/acl-org/acl-anthology/",
    "2025": "/events/iwsds-2025/",
    "Proceedings of the 15th International Workshop on Spoken Dialogue Systems Technology": "/volumes/2025.iwsds-1/",
    "": "http://creativecommons.org/licenses/by/4.0/",
    "Creative Commons Attribution-NonCommercial-ShareAlike 3.0 International License": "https://creativecommons.org/licenses/by-nc-sa/3.0/",
    "Creative Commons Attribution 4.0 International License": "https://creativecommons.org/licenses/by/4.0/",
    "ACL Anthology team": "/info/credits/",
    "commit efd9fde": "https://github.com/acl-org/acl-anthology/tree/efd9fde4dd69796c3043adab08e67bb462df049d"
  },
  "_meta": {
    "source_url": "https://aclanthology.org/venues/iwsds/",
    "fetch_mode": "FAST",
    "site": "generic",
    "html_path": "data/html/aclanthology.org_venues_iwsds/rendered.html",
    "quality": {
      "score": 3,
      "status": "ok"
    }
  }
}